LICENSE
MANIFEST.in
README.rst
setup.py
Shoot.egg-info/PKG-INFO
Shoot.egg-info/SOURCES.txt
Shoot.egg-info/dependency_links.txt
Shoot.egg-info/entry_points.txt
Shoot.egg-info/requires.txt
Shoot.egg-info/top_level.txt
shoot/__init__.py
shoot/django_settings.py
shoot/run.py
shoot/server.py