Metadata-Version: 1.0
Name: Shoot
Version: 0.1.0
Summary: Kick-start your prototype with Django templates
Home-page: https://github.com/pcx/shoot
Author: Phaneendra Chiruvella
Author-email: hi@pcx.io
License: The MIT License (MIT)
